checkngn/__init__.py
checkngn/actions.py
checkngn/engine.py
checkngn/fields.py
checkngn/logs.py
checkngn/operators.py
checkngn/utils.py
checkngn/variables.py
checkngn-0.1.4.dist-info/METADATA
checkngn-0.1.4.dist-info/WHEEL
checkngn-0.1.4.dist-info/licenses/LICENSE
checkngn-0.1.4.dist-info/RECORD
