Metadata-Version: 2.4
Name: checkngn
Version: 0.1.4
Summary: A lightweight Python DSL for setting up business intelligence rules that can be configured without code.
Project-URL: Homepage, https://github.com/AhnafCodes/checkngn
Author: AhnafCodes
License-Expression: MIT
License-File: LICENSE
Classifier: License :: OSI Approved :: MIT License
Classifier: Operating System :: OS Independent
Classifier: Programming Language :: Python :: 3
Classifier: Programming Language :: Python :: 3.13
Classifier: Programming Language :: Python :: 3.14
Requires-Python: >=3.13
Requires-Dist: numpy>=2.4.0
Requires-Dist: pandas>=2.3.3
Requires-Dist: python-dateutil
Requires-Dist: pyyaml>=6.0.3
Provides-Extra: dev
Requires-Dist: mock>=5.0.0; extra == 'dev'
Requires-Dist: pandas>=2.3.3; extra == 'dev'
Requires-Dist: pytest>=8.0.0; extra == 'dev'
